oxionics_qiskit_provider/__init__.py
oxionics_qiskit_provider/backend.py
oxionics_qiskit_provider/job.py
oxionics_qiskit_provider/provider.py
oxionics_qiskit_provider-0.1.1.dist-info/WHEEL
oxionics_qiskit_provider-0.1.1.dist-info/METADATA
oxionics_qiskit_provider-0.1.1.dist-info/RECORD
