Metadata-Version: 2.1
Name: oxionics-qiskit-provider
Version: 0.1.1
Summary: 
License: MIT
Author: Oxford Ionics
Requires-Python: >=3.8,<4.0
Classifier: License :: OSI Approved :: MIT License
Classifier: Programming Language :: Python :: 3
Classifier: Programming Language :: Python :: 3.8
Classifier: Programming Language :: Python :: 3.9
Classifier: Programming Language :: Python :: 3.10
Classifier: Programming Language :: Python :: 3.11
Requires-Dist: qiskit-terra (>=0.23.1,<0.24.0)
Requires-Dist: requests (>=2.28.2,<3.0.0)
